wulkanowy_qr/__init__.py
wulkanowy_qr-1.0.1.dist-info/METADATA
wulkanowy_qr-1.0.1.dist-info/WHEEL
wulkanowy_qr-1.0.1.dist-info/top_level.txt
wulkanowy_qr-1.0.1.dist-info/RECORD
