Metadata-Version: 2.1
Name: wulkanowy-qr
Version: 1.0.1
Summary: UONET+ QR Code converter for Python
Author-email: JelNiSlaw <jelnislaw@gmail.com>
License: MIT
Project-URL: Repository, https://github.com/wulkanowy/qr/tree/master/python
Requires-Dist: pycryptodome (~=3.15)
